chb/__init__.py
chb/_dao.py
chb/_importable.py
chb/_imports.py
chb/_log.py
chb/_utils.py
chb-2.1.7.dist-info/LICENSE.txt
chb-2.1.7.dist-info/METADATA
chb-2.1.7.dist-info/WHEEL
chb-2.1.7.dist-info/top_level.txt
chb-2.1.7.dist-info/RECORD
