Metadata-Version: 2.1
Name: chb
Version: 2.1.7
Summary: chb常用代码库
Home-page: https://github.com/ChenHuabin321/pypi
Author: chenhuabin
Author-email: chenhuabin321@163.com
Classifier: Programming Language :: Python :: 3
Classifier: License :: OSI Approved :: MIT License
Classifier: Operating System :: OS Independent
Requires-Python: >=3.6
License-File: LICENSE.txt
